fastfcgr/FastFCGR.py
fastfcgr/__init__.py
fastfcgr-1.0.0.dist-info/METADATA
fastfcgr-1.0.0.dist-info/WHEEL
fastfcgr-1.0.0.dist-info/licenses/LICENSE
fastfcgr-1.0.0.dist-info/RECORD
