Metadata-Version: 2.4
Name: fastfcgr
Version: 1.0.0
Summary: FCGR class (Frequency Chaos Game Representation)
Project-URL: Homepage, https://github.com/FilippoTib/FastFCGR
Project-URL: Issues, https://github.com/FilippoTib/FastFCGR/issues
Author-email: Filippo Tiberio <filippo.tiberio@studenti.unipd.it>
License-File: LICENSE
Classifier: Development Status :: 4 - Beta
Classifier: License :: OSI Approved :: MIT License
Classifier: Operating System :: OS Independent
Classifier: Programming Language :: Python :: 3
Requires-Python: >=3.8
